ofusion/__init__.py
ofusion-0.0.1.dev1.dist-info/METADATA
ofusion-0.0.1.dev1.dist-info/WHEEL
ofusion-0.0.1.dev1.dist-info/top_level.txt
ofusion-0.0.1.dev1.dist-info/RECORD
