Metadata-Version: 2.2
Name: ofusion
Version: 0.0.1.dev1
Summary: A Domain-Specific Language for High-Performance Creative Coding with openFrameworks
Home-page: https://github.com/yourusername/ofusion
Author: Bairui Su
Author-email: subairui@icloud.com
Classifier: Programming Language :: Python :: 3
Classifier: License :: OSI Approved :: MIT License
Classifier: Operating System :: OS Independent
Requires-Python: >=3.7
Dynamic: author
Dynamic: author-email
Dynamic: classifier
Dynamic: home-page
Dynamic: requires-python
Dynamic: summary
